<?xml version="1.0" encoding="utf-8"?>
<ode><userPreferences><userPreference><key>theme</key><value>base</value></userPreference></userPreferences><odeResources><odeResource><key>odeVersionId</key><value>20260430094221UTAZQJ</value></odeResource><odeResource><key>odeId</key><value>20260430085210OPYXLS</value></odeResource><odeResource><key>odeVersionName</key><value>0</value></odeResource><odeResource><key>isDownload</key><value>true</value></odeResource><odeResource><key>eXeVersion</key><value>v3.0.2</value></odeResource></odeResources><odeProperties><odeProperty><key>pp_title</key><value>SdA Funciones</value></odeProperty><odeProperty><key>pp_subtitle</key><value>asdfasdf</value></odeProperty><odeProperty><key>pp_lang</key><value>es</value></odeProperty><odeProperty><key>pp_author</key><value>aco</value></odeProperty><odeProperty><key>license</key><value>creative commons: attribution - share alike 4.0</value></odeProperty><odeProperty><key>pp_description</key><value>sda mate</value></odeProperty><odeProperty><key>exportSource</key><value>true</value></odeProperty><odeProperty><key>pp_addExeLink</key><value>true</value></odeProperty><odeProperty><key>pp_addPagination</key><value>false</value></odeProperty><odeProperty><key>pp_addSearchBox</key><value>false</value></odeProperty><odeProperty><key>pp_addAccessibilityToolbar</key><value>false</value></odeProperty><odeProperty><key>pp_extraHeadContent</key><value/></odeProperty><odeProperty><key>footer</key><value/></odeProperty></odeProperties><odeNavStructures><odeNavStructure><odePageId>20260430094221FTPHYO</odePageId><odeParentPageId/><pageName>SdA Funciones</pageName><odeNavStructureOrder>1</odeNavStructureOrder><odeNavStructureProperties><odeNavStructureProperty><key>titleNode</key><value/></odeNavStructureProperty><odeNavStructureProperty><key>hidePageTitle</key><value>false</value></odeNavStructureProperty><odeNavStructureProperty><key>titleHtml</key><value/></odeNavStructureProperty><odeNavStructureProperty><key>editableInPage</key><value>false</value></odeNavStructureProperty><odeNavStructureProperty><key>titlePage</key><value>SdA Funciones</value></odeNavStructureProperty><odeNavStructureProperty><key>visibility</key><value>true</value></odeNavStructureProperty><odeNavStructureProperty><key>highlight</key><value>false</value></odeNavStructureProperty><odeNavStructureProperty><key>description</key><value/></odeNavStructureProperty></odeNavStructureProperties><odePagStructures><odePagStructure><odePageId>20260430094221FTPHYO</odePageId><odeBlockId>20260430094221YDFLNE</odeBlockId><blockName>Texto</blockName><iconName/><odePagStructureOrder>1</odePagStructureOrder><odePagStructureProperties><odePagStructureProperty><key>visibility</key><value>true</value></odePagStructureProperty><odePagStructureProperty><key>teacherOnly</key><value>false</value></odePagStructureProperty><odePagStructureProperty><key>allowToggle</key><value>true</value></odePagStructureProperty><odePagStructureProperty><key>minimized</key><value>false</value></odePagStructureProperty><odePagStructureProperty><key>identifier</key><value/></odePagStructureProperty><odePagStructureProperty><key>cssClass</key><value/></odePagStructureProperty></odePagStructureProperties><odeComponents><odeComponent><odePageId>20260430094221FTPHYO</odePageId><odeBlockId>20260430094221YDFLNE</odeBlockId><odeIdeviceId>20260424110959329Z6K</odeIdeviceId><odeIdeviceTypeName>text</odeIdeviceTypeName><htmlView>&lt;div class="exe-text-template"&gt;&lt;div class="textIdeviceContent"&gt;
            &lt;div class="exe-text-activity"&gt;
                &lt;div&gt;&lt;p&gt;DESCRIPCIÓN DE LA SdA&lt;/p&gt;
&lt;p&gt;&lt;strong&gt;Etapa:&lt;/strong&gt;&amp;nbsp;Esta situación de aprendizaje está orientada al segundo nivel del primer ciclo de educación secundaria obligatoria.&lt;/p&gt;
&lt;p&gt;&lt;strong&gt;Área:&lt;/strong&gt; Matemáticas&lt;/p&gt;
&lt;p&gt;&lt;strong&gt;Agrupamientos y organización espacial:&lt;/strong&gt; Los agrupamientos variarán en función de la actividad, alternando gran grupo, pequeño grupo (división de la clase en grupos de 4 personas) y trabajo individual. Los agrupamientos serán heterogéneos y flexibles.&lt;/p&gt;
&lt;p&gt;&lt;strong&gt;Temporalización:&lt;/strong&gt; tercer trimestre ( 3 sesiones de 55minutos)&lt;/p&gt;
&lt;p&gt;&lt;em&gt;Sesión 1&lt;/em&gt;: explicación de términos básicos de funciones lineales, tales como la ecuación de la recta, la pendiente y el corte con el eje y. Realización de ejercicios.&lt;/p&gt;
&lt;p&gt;&lt;em&gt;Sesión 2&lt;/em&gt;: realización de una infografía resumen de los contenidos aprendidos en la sesión 1 mediante la aplicación Canva.&lt;/p&gt;
&lt;p&gt;&lt;em&gt;Sesión 3&lt;/em&gt;: aplicación de los conceptos estudiados en las sesiones anteriores mediante gamificación para la realización de un breakout.&lt;/p&gt;
&lt;p&gt;&lt;br&gt;&lt;/p&gt;
&lt;p&gt;&lt;strong&gt;Productos intermedios y producto final:&lt;/strong&gt; el producto intermedio será la realización de una infografía en Canva. El producto final será la realización de un breakout a modo de "Scape Room" en el que el alumnado (dividido en grupos) competirá por resolver una serie de problemas y acertijos.&lt;/p&gt;
&lt;p&gt;&lt;strong&gt;Herramientas tecnológicas:&lt;/strong&gt; ordenador, pizarra digital, internet, Teams, One drive, Canva.&lt;/p&gt;
&lt;p&gt;&lt;br&gt;&lt;/p&gt;&lt;p class="clearfix"&gt;&lt;/p&gt;&lt;/div&gt;
            &lt;/div&gt;&lt;/div&gt;&lt;/div&gt;</htmlView><jsonProperties>{"ideviceId":"20260424110959329Z6K","textInfoDurationInput":"","textInfoDurationTextInput":"Duración","textInfoParticipantsInput":"","textInfoParticipantsTextInput":"Agrupamiento","textTextarea":"&lt;p&gt;DESCRIPCIÓN DE LA SdA&lt;/p&gt;\n&lt;p&gt;&lt;strong&gt;Etapa:&lt;/strong&gt; Esta situación de aprendizaje está orientada al segundo nivel del primer ciclo de educación secundaria obligatoria.&lt;/p&gt;\n&lt;p&gt;&lt;strong&gt;Área:&lt;/strong&gt; Matemáticas&lt;/p&gt;\n&lt;p&gt;&lt;strong&gt;Agrupamientos y organización espacial:&lt;/strong&gt; Los agrupamientos variarán en función de la actividad, alternando gran grupo, pequeño grupo (división de la clase en grupos de 4 personas) y trabajo individual. Los agrupamientos serán heterogéneos y flexibles.&lt;/p&gt;\n&lt;p&gt;&lt;strong&gt;Temporalización:&lt;/strong&gt; tercer trimestre ( 3 sesiones de 55minutos)&lt;/p&gt;\n&lt;p&gt;&lt;em&gt;Sesión 1&lt;/em&gt;: explicación de términos básicos de funciones lineales, tales como la ecuación de la recta, la pendiente y el corte con el eje y. Realización de ejercicios.&lt;/p&gt;\n&lt;p&gt;&lt;em&gt;Sesión 2&lt;/em&gt;: realización de una infografía resumen de los contenidos aprendidos en la sesión 1 mediante la aplicación Canva.&lt;/p&gt;\n&lt;p&gt;&lt;em&gt;Sesión 3&lt;/em&gt;: aplicación de los conceptos estudiados en las sesiones anteriores mediante gamificación para la realización de un breakout.&lt;/p&gt;\n&lt;p&gt;&lt;br /&gt;&lt;/p&gt;\n&lt;p&gt;&lt;strong&gt;Productos intermedios y producto final:&lt;/strong&gt; el producto intermedio será la realización de una infografía en Canva. El producto final será la realización de un breakout a modo de \"Scape Room\" en el que el alumnado (dividido en grupos) competirá por resolver una serie de problemas y acertijos.&lt;/p&gt;\n&lt;p&gt;&lt;strong&gt;Herramientas tecnológicas:&lt;/strong&gt; ordenador, pizarra digital, internet, Teams, One drive, Canva.&lt;/p&gt;\n&lt;p&gt;&lt;br /&gt;&lt;/p&gt;","textFeedbackInput":"Mostrar retroalimentación","textFeedbackTextarea":""}</jsonProperties><odeComponentsOrder>1</odeComponentsOrder><odeComponentsProperties><odeComponentsProperty><key>visibility</key><value>true</value></odeComponentsProperty><odeComponentsProperty><key>teacherOnly</key><value>false</value></odeComponentsProperty><odeComponentsProperty><key>identifier</key><value/></odeComponentsProperty><odeComponentsProperty><key>cssClass</key><value/></odeComponentsProperty></odeComponentsProperties></odeComponent></odeComponents></odePagStructure></odePagStructures></odeNavStructure><odeNavStructure><odePageId>20260430094221NFEBNT</odePageId><odeParentPageId>20260430094221FTPHYO</odeParentPageId><pageName>1. Intención educativa</pageName><odeNavStructureOrder>1</odeNavStructureOrder><odeNavStructureProperties><odeNavStructureProperty><key>titleNode</key><value/></odeNavStructureProperty><odeNavStructureProperty><key>hidePageTitle</key><value>false</value></odeNavStructureProperty><odeNavStructureProperty><key>titleHtml</key><value/></odeNavStructureProperty><odeNavStructureProperty><key>editableInPage</key><value>false</value></odeNavStructureProperty><odeNavStructureProperty><key>titlePage</key><value>1. Intención educativa</value></odeNavStructureProperty><odeNavStructureProperty><key>visibility</key><value>true</value></odeNavStructureProperty><odeNavStructureProperty><key>highlight</key><value>false</value></odeNavStructureProperty><odeNavStructureProperty><key>description</key><value/></odeNavStructureProperty></odeNavStructureProperties><odePagStructures><odePagStructure><odePageId>20260430094221NFEBNT</odePageId><odeBlockId>20260430094221SLYDIH</odeBlockId><blockName>Texto</blockName><iconName/><odePagStructureOrder>1</odePagStructureOrder><odePagStructureProperties><odePagStructureProperty><key>visibility</key><value>true</value></odePagStructureProperty><odePagStructureProperty><key>teacherOnly</key><value>false</value></odePagStructureProperty><odePagStructureProperty><key>allowToggle</key><value>true</value></odePagStructureProperty><odePagStructureProperty><key>minimized</key><value>false</value></odePagStructureProperty><odePagStructureProperty><key>identifier</key><value/></odePagStructureProperty><odePagStructureProperty><key>cssClass</key><value/></odePagStructureProperty></odePagStructureProperties><odeComponents><odeComponent><odePageId>20260430094221NFEBNT</odePageId><odeBlockId>20260430094221SLYDIH</odeBlockId><odeIdeviceId>20260424111123532TKU</odeIdeviceId><odeIdeviceTypeName>text</odeIdeviceTypeName><htmlView>&lt;div class="exe-text-template"&gt;&lt;div class="textIdeviceContent"&gt;
            &lt;div class="exe-text-activity"&gt;
                &lt;div&gt;&lt;p&gt;&lt;strong&gt;Justificación de su desarrollo y el impacto esperado.&lt;/strong&gt;&lt;/p&gt;
&lt;p&gt;Las funciones forman parte de la programación de 2ºESO, mediante esta SdA relacionada con el Proyecto de Educación para la Salud, se pretende acercar al alumnado a la materia de una forma práctica y&amp;nbsp; atractiva para su comprensión.&lt;/p&gt;
&lt;p&gt;Con esta SdA se intenta promover la colaboración y el trabajo en equipo, fomentar la comunicación al compartir ideas y técnicas, así como respetar las opiniones del resto de personas.&lt;/p&gt;
&lt;p&gt;Se espera que al finalizar la SdA, el alumnado sea capaz de reconocer los principales componentes de las funciones y asociarlos a ejemplos de la vida cotidiana como pueden ser el reparto de alimentos y el buen aprovechamiento de los mismos.&lt;/p&gt;
&lt;p&gt;&lt;br&gt;Esta SdA está relacionada con:&lt;/p&gt;
&lt;p&gt;&lt;strong&gt;Objetivos de desarrollo sostenible:&lt;/strong&gt;&lt;/p&gt;
&lt;ul&gt;
&lt;li&gt;ODS 2: Hambre Cero&lt;/li&gt;
&lt;li&gt;ODS 3: Salud y Bienestar&lt;/li&gt;
&lt;li&gt;ODS 12: Producción y Consumo Responsables&lt;/li&gt;
&lt;/ul&gt;
&lt;p&gt;&lt;strong&gt;Retos del siglo XXI:&lt;/strong&gt;&lt;/p&gt;
&lt;ol&gt;
&lt;li&gt;&amp;nbsp;Identificar los diferentes aspectos relacionados con el consumo responsable, valorando sus repercusiones sobre el bien individual y el común, juzgando críticamente las necesidades y los excesos y ejerciendo un control social frente a la vulneración de sus derechos.&lt;/li&gt;
&lt;li&gt;Desarrollar estilos de vida saludable a partir de la comprensión del funcionamiento del organismo y la reflexión crítica sobre los factores internos y externos que inciden en ella, asumiendo la responsabilidad personal y social en el cuidado propio y en el cuidado de las demás personas, así como en la promoción de la salud pública.&lt;/li&gt;
&lt;li&gt;Desarrollar un espíritu crítico, empático y proactivo para detectar situaciones de inequidad y exclusión a partir de la comprensión de las causas complejas que las originan.&lt;/li&gt;
&lt;li&gt;Sentirse parte de un proyecto colectivo, tanto en el ámbito local como en el global, desarrollando empatía y generosidad.&lt;/li&gt;
&lt;li&gt;Desarrollar las habilidades que le permitan seguir aprendiendo a lo largo de la vida, desde la confianza en el conocimiento como motor del desarrollo y la valoración crítica de los riesgos y beneficios de este último.&lt;/li&gt;
&lt;/ol&gt;&lt;p class="clearfix"&gt;&lt;/p&gt;&lt;/div&gt;
            &lt;/div&gt;&lt;/div&gt;&lt;/div&gt;</htmlView><jsonProperties>{"ideviceId":"20260424111123532TKU","textInfoDurationInput":"","textInfoDurationTextInput":"Duración","textInfoParticipantsInput":"","textInfoParticipantsTextInput":"Agrupamiento","textTextarea":"&lt;p&gt;&lt;strong&gt;Justificación de su desarrollo y el impacto esperado.&lt;/strong&gt;&lt;/p&gt;\n&lt;p&gt;Las funciones forman parte de la programación de 2ºESO, mediante esta SdA relacionada con el Proyecto de Educación para la Salud, se pretende acercar al alumnado a la materia de una forma práctica y  atractiva para su comprensión.&lt;/p&gt;\n&lt;p&gt;Con esta SdA se intenta promover la colaboración y el trabajo en equipo, fomentar la comunicación al compartir ideas y técnicas, así como respetar las opiniones del resto de personas.&lt;/p&gt;\n&lt;p&gt;Se espera que al finalizar la SdA, el alumnado sea capaz de reconocer los principales componentes de las funciones y asociarlos a ejemplos de la vida cotidiana como pueden ser el reparto de alimentos y el buen aprovechamiento de los mismos.&lt;/p&gt;\n&lt;p&gt;&lt;br /&gt;Esta SdA está relacionada con:&lt;/p&gt;\n&lt;p&gt;&lt;strong&gt;Objetivos de desarrollo sostenible:&lt;/strong&gt;&lt;/p&gt;\n&lt;ul&gt;\n&lt;li&gt;ODS 2: Hambre Cero&lt;/li&gt;\n&lt;li&gt;ODS 3: Salud y Bienestar&lt;/li&gt;\n&lt;li&gt;ODS 12: Producción y Consumo Responsables&lt;/li&gt;\n&lt;/ul&gt;\n&lt;p&gt;&lt;strong&gt;Retos del siglo XXI:&lt;/strong&gt;&lt;/p&gt;\n&lt;ol&gt;\n&lt;li&gt; Identificar los diferentes aspectos relacionados con el consumo responsable, valorando sus repercusiones sobre el bien individual y el común, juzgando críticamente las necesidades y los excesos y ejerciendo un control social frente a la vulneración de sus derechos.&lt;/li&gt;\n&lt;li&gt;Desarrollar estilos de vida saludable a partir de la comprensión del funcionamiento del organismo y la reflexión crítica sobre los factores internos y externos que inciden en ella, asumiendo la responsabilidad personal y social en el cuidado propio y en el cuidado de las demás personas, así como en la promoción de la salud pública.&lt;/li&gt;\n&lt;li&gt;Desarrollar un espíritu crítico, empático y proactivo para detectar situaciones de inequidad y exclusión a partir de la comprensión de las causas complejas que las originan.&lt;/li&gt;\n&lt;li&gt;Sentirse parte de un proyecto colectivo, tanto en el ámbito local como en el global, desarrollando empatía y generosidad.&lt;/li&gt;\n&lt;li&gt;Desarrollar las habilidades que le permitan seguir aprendiendo a lo largo de la vida, desde la confianza en el conocimiento como motor del desarrollo y la valoración crítica de los riesgos y beneficios de este último.&lt;/li&gt;\n&lt;/ol&gt;","textFeedbackInput":"Mostrar retroalimentación","textFeedbackTextarea":""}</jsonProperties><odeComponentsOrder>1</odeComponentsOrder><odeComponentsProperties><odeComponentsProperty><key>visibility</key><value>true</value></odeComponentsProperty><odeComponentsProperty><key>teacherOnly</key><value>false</value></odeComponentsProperty><odeComponentsProperty><key>identifier</key><value/></odeComponentsProperty><odeComponentsProperty><key>cssClass</key><value/></odeComponentsProperty></odeComponentsProperties></odeComponent></odeComponents></odePagStructure></odePagStructures></odeNavStructure><odeNavStructure><odePageId>20260430094221DORAFX</odePageId><odeParentPageId>20260430094221FTPHYO</odeParentPageId><pageName>2. Elementos curriculares</pageName><odeNavStructureOrder>2</odeNavStructureOrder><odeNavStructureProperties><odeNavStructureProperty><key>titleNode</key><value/></odeNavStructureProperty><odeNavStructureProperty><key>hidePageTitle</key><value>false</value></odeNavStructureProperty><odeNavStructureProperty><key>titleHtml</key><value/></odeNavStructureProperty><odeNavStructureProperty><key>editableInPage</key><value>false</value></odeNavStructureProperty><odeNavStructureProperty><key>titlePage</key><value>2. Elementos curriculares</value></odeNavStructureProperty><odeNavStructureProperty><key>visibility</key><value>true</value></odeNavStructureProperty><odeNavStructureProperty><key>highlight</key><value>false</value></odeNavStructureProperty><odeNavStructureProperty><key>description</key><value/></odeNavStructureProperty></odeNavStructureProperties><odePagStructures><odePagStructure><odePageId>20260430094221DORAFX</odePageId><odeBlockId>20260430094221TXVTEG</odeBlockId><blockName>Texto</blockName><iconName/><odePagStructureOrder>1</odePagStructureOrder><odePagStructureProperties><odePagStructureProperty><key>visibility</key><value>true</value></odePagStructureProperty><odePagStructureProperty><key>teacherOnly</key><value>false</value></odePagStructureProperty><odePagStructureProperty><key>allowToggle</key><value>true</value></odePagStructureProperty><odePagStructureProperty><key>minimized</key><value>false</value></odePagStructureProperty><odePagStructureProperty><key>identifier</key><value/></odePagStructureProperty><odePagStructureProperty><key>cssClass</key><value/></odePagStructureProperty></odePagStructureProperties><odeComponents><odeComponent><odePageId>20260430094221DORAFX</odePageId><odeBlockId>20260430094221TXVTEG</odeBlockId><odeIdeviceId>20260424111208209RO5</odeIdeviceId><odeIdeviceTypeName>text</odeIdeviceTypeName><htmlView>&lt;div class="exe-text-template"&gt;&lt;div class="textIdeviceContent"&gt;
            &lt;div class="exe-text-activity"&gt;
                &lt;div&gt;&lt;p&gt;&lt;/p&gt;
&lt;table border="1" style="width: 99.9778%; height: 2236.8px; border-color: #169179; border-style: outset;"&gt;
&lt;tbody&gt;
&lt;tr style="height: 50.4px;"&gt;
&lt;td style="width: 39.0782%; height: 50.4px;"&gt;&lt;strong&gt;COMPETENCIA ESPECÍFICA&lt;/strong&gt;&lt;/td&gt;
&lt;td style="width: 14.4719%; height: 50.4px;"&gt;&lt;strong&gt;DESCRIPTORES DEL PERFIL DE SALIDA&lt;/strong&gt;&lt;/td&gt;
&lt;td style="width: 46.3163%; height: 50.4px;"&gt;&lt;strong&gt;CRITERIOS DE EVALUACIÓN&lt;/strong&gt;&lt;/td&gt;
&lt;/tr&gt;
&lt;tr style="height: 362px;"&gt;
&lt;td style="width: 39.0782%; height: 362px;"&gt;
&lt;p&gt;&lt;strong&gt;CE1. Competencia específica&amp;nbsp;&lt;/strong&gt;&lt;/p&gt;
&lt;p&gt;Interpretar, modelizar y resolver problemas de la vida cotidiana propios de las matemáticas aplicando diferentes estrategias y formas de razonamiento para explorar distintas maneras de proceder y obtener posibles soluciones. &amp;nbsp;&lt;/p&gt;
&lt;/td&gt;
&lt;td style="width: 14.4719%; height: 362px;"&gt;STEM1, STEM2, STEM3, STEM 4, CD2, CPSAA5, CE3, CCEC4. &amp;nbsp;&lt;/td&gt;
&lt;td style="width: 46.3163%; height: 362px;"&gt;CE1.1. Interpretar problemas matemáticos organizando los datos dados, estableciendo las relaciones entre ellos y comprendiendo las preguntas formuladas. &amp;nbsp;&lt;br&gt;CE1.2. Aplicar herramientas y estrategias apropiadas que contribuyan a la resolución de problemas.  &amp;nbsp;&lt;br&gt;CE1.3. Obtener soluciones matemáticas de un problema activando los conocimientos y utilizando las herramientas tecnológicas necesarias. &amp;nbsp;&lt;/td&gt;
&lt;/tr&gt;
&lt;tr style="height: 274px;"&gt;
&lt;td style="width: 39.0782%; height: 274px;"&gt;
&lt;p&gt;&lt;strong&gt;CE2. Competencia específica&lt;/strong&gt;&amp;nbsp;&lt;/p&gt;
&lt;p&gt;&amp;nbsp;Analizar las soluciones de un problema usando diferentes técnicas y herramientas, evaluando las respuestas obtenidas, para verificar su validez e idoneidad desde un punto de vista matemático y su repercusión global. &amp;nbsp;&lt;/p&gt;
&lt;/td&gt;
&lt;td style="width: 14.4719%; height: 274px;"&gt;STEM1, STEM2, CD2, CPSAA4, CC3, CE3. &amp;nbsp;&lt;/td&gt;
&lt;td style="width: 46.3163%; height: 274px;"&gt;
&lt;p&gt;CE2.2. Comprobar la validez de las soluciones de un problema y su coherencia en el contexto planteado, evaluando el alcance y repercusión de estas desde diferentes perspectivas (de género, de sostenibilidad, de consumo responsable, etc.). &amp;nbsp;&lt;/p&gt;
&lt;/td&gt;
&lt;/tr&gt;
&lt;tr style="height: 578px;"&gt;
&lt;td style="width: 39.0782%; height: 578px;"&gt;
&lt;p&gt;&lt;strong&gt;CE 6.Competencia específica&lt;/strong&gt;&amp;nbsp;&lt;/p&gt;
&lt;p&gt;Identificar las matemáticas implicadas en otras materias y en situaciones reales, susceptibles de ser abordadas en términos matemáticos, interrelacionando conceptos y procedimientos para aplicarlos en situaciones diversas. &amp;nbsp;&lt;/p&gt;
&lt;p&gt;&lt;br&gt;&lt;/p&gt;
&lt;/td&gt;
&lt;td style="width: 14.4719%; height: 578px;"&gt;&amp;nbsp;STEM1, STEM3, CD3, CD5, CC4, CE2, CE3, CCEC1. &amp;nbsp;&lt;/td&gt;
&lt;td style="width: 46.3163%; height: 578px;"&gt;CE6.1. Reconocer situaciones susceptibles de ser formuladas y resueltas mediante herramientas y estrategias matemáticas, estableciendo conexiones entre el mundo real y las matemáticas y usando los procesos inherentes a la investigación: inferir, medir, comunicar, clasificar y predecir. &amp;nbsp;&lt;br&gt;CE6.2. Identificar conexiones coherentes entre las matemáticas y otras materias resolviendo problemas contextualizados. &amp;nbsp;&lt;br&gt;CE6.3. Reconocer la aportación de las matemáticas al progreso de la humanidad y su contribución a la superación de los retos que demanda la sociedad actual. &amp;nbsp;&lt;/td&gt;
&lt;/tr&gt;
&lt;tr style="height: 410px;"&gt;
&lt;td style="width: 39.0782%; height: 410px;"&gt;
&lt;p&gt;&lt;strong&gt;CE 7.Competencia específica&lt;/strong&gt; Representar, de forma individual y colectiva, conceptos, procedimientos, información y resultados matemáticos usando diferentes tecnologías, para visualizar ideas y estructurar procesos matemáticos.  &amp;nbsp;&lt;/p&gt;
&lt;p&gt; &amp;nbsp;&lt;/p&gt;
&lt;/td&gt;
&lt;td style="width: 14.4719%; height: 410px;"&gt;STEM3, CD1, CD2, CD5, CE3, CCEC4.&lt;/td&gt;
&lt;td style="width: 46.3163%; height: 410px;"&gt;CE7.1. Representar conceptos, procedimientos, información y resultados matemáticos de modos distintos y con diferentes herramientas, incluidas las digitales, visualizando ideas, estructurando procesos matemáticos y valorando su utilidad para compartir información. &amp;nbsp;&lt;br&gt;CE7.2. Elaborar representaciones matemáticas que ayuden en la búsqueda de estrategias de resolución de una situación problematizada. &amp;nbsp;&lt;/td&gt;
&lt;/tr&gt;
&lt;tr style="height: 458px;"&gt;
&lt;td style="width: 39.0782%; height: 458px;"&gt;
&lt;p&gt;&lt;strong&gt;CE 9. Competencia específica&amp;nbsp;&lt;/strong&gt;&lt;/p&gt;
&lt;p&gt;&amp;nbsp;Desarrollar destrezas personales, identificando y gestionando emociones, poniendo en práctica estrategias de aceptación del error como parte del proceso de aprendizaje y adaptándose ante situaciones de incertidumbre, para mejorar la perseverancia en la consecución de objetivos y el disfrute en el aprendizaje de las matemáticas. &amp;nbsp;&lt;/p&gt;
&lt;p&gt;&amp;nbsp;&lt;/p&gt;
&lt;/td&gt;
&lt;td style="width: 14.4719%; height: 458px;"&gt;&amp;nbsp;STEM5, CPSAA1, CPSAA4, CPSAA5, CE2, CE3.&lt;/td&gt;
&lt;td style="width: 46.3163%; height: 458px;"&gt;CE9.1. Gestionar las emociones propias, desarrollar el autoconcepto matemático como herramienta generando expectativas positivas ante nuevos retos matemáticos. &amp;nbsp;&lt;br&gt;CE9.2. Mostrar una actitud positiva y perseverante, aceptando la crítica razonada al hacer frente a las diferentes situaciones de aprendizaje de las matemáticas. &amp;nbsp;&lt;/td&gt;
&lt;/tr&gt;
&lt;tr style="height: 26px;"&gt;
&lt;td style="width: 39.0782%; height: 26px;"&gt;
&lt;p&gt;&lt;strong&gt;CE 10. Competencia específica&lt;/strong&gt; Desarrollar destrezas sociales reconociendo y respetando las emociones y experiencias ajenas, participando activa y reflexivamente en proyectos en equipos heterogéneos con roles asignados para construir una identidad positiva como estudiante de matemáticas, fomentar el bienestar personal y grupal y crear relaciones saludables. &amp;nbsp; &amp;nbsp;&lt;/p&gt;
&lt;/td&gt;
&lt;td style="width: 14.4719%; height: 26px;"&gt;CCL5, CP3, STEM3, CPSAA1, CPSAA3, CC2, CC3.&lt;/td&gt;
&lt;td style="width: 46.3163%; height: 26px;"&gt;CE10.1. Colaborar activamente y construir relaciones trabajando con las matemáticas en equipos heterogéneos, respetando diferentes opiniones, comunicándose de manera efectiva, pensando de forma crítica y creativa y tomando decisiones y realizando juicios informados. &amp;nbsp;&lt;br&gt;CE10.2. Participar en el reparto de tareas que deban desarrollarse en equipo, aportando valor, favoreciendo la inclusión, la escucha activa, asumiendo el rol asignado y responsabilizándose de la propia contribución al equipo. &amp;nbsp;&lt;/td&gt;
&lt;/tr&gt;
&lt;tr style="height: 26px;"&gt;
&lt;td style="width: 39.0782%; height: 26px;"&gt;&lt;br&gt;&lt;/td&gt;
&lt;td style="width: 14.4719%; height: 26px;"&gt;&lt;br&gt;&lt;/td&gt;
&lt;td style="width: 46.3163%; height: 26px;"&gt;&lt;br&gt;&lt;/td&gt;
&lt;/tr&gt;
&lt;tr style="height: 26px;"&gt;
&lt;td style="width: 39.0782%; height: 26px;"&gt;&lt;br&gt;&lt;/td&gt;
&lt;td style="width: 14.4719%; height: 26px;"&gt;&lt;br&gt;&lt;/td&gt;
&lt;td style="width: 46.3163%; height: 26px;"&gt;&lt;br&gt;&lt;/td&gt;
&lt;/tr&gt;
&lt;tr style="height: 26.4px;"&gt;
&lt;td style="width: 39.0782%; height: 26.4px;"&gt;&lt;br&gt;&lt;/td&gt;
&lt;td style="width: 14.4719%; height: 26.4px;"&gt;&lt;br&gt;&lt;/td&gt;
&lt;td style="width: 46.3163%; height: 26.4px;"&gt;&lt;/td&gt;
&lt;/tr&gt;
&lt;/tbody&gt;
&lt;/table&gt;
&lt;p&gt;&lt;br&gt;&lt;br&gt;&lt;strong&gt;SABERES BÁSICOS&lt;/strong&gt;&lt;/p&gt;
&lt;p&gt;&lt;strong&gt;Bloque D. Sentido algebraico y pensamiento computacional:&lt;/strong&gt;&lt;/p&gt;
&lt;ul&gt;
&lt;li&gt;Patrones&lt;br&gt;- Patrones: observación en casos sencillos.&lt;br&gt;Bloque D. Sentido algebraico y pensamiento computacional: Modelo matemático&lt;br&gt;- Modelización de situaciones de la vida cotidiana usando representaciones matemáticas y el lenguaje algebraico.- Estrategias de deducción de conclusiones razonables a partir de un modelo matemático.&lt;/li&gt;
&lt;li&gt;Variable: Comprensión del concepto de variable en sus diferentes naturalezas.&lt;/li&gt;
&lt;/ul&gt;
&lt;ul&gt;
&lt;li&gt;&amp;nbsp;Igualdad y desigualdad:&lt;/li&gt;
&lt;/ul&gt;
&lt;p&gt;- Relaciones lineales y cuadráticas en situaciones de la vida cotidiana o matemáticamente relevantes: expresión mediante álgebra simbólica.&lt;/p&gt;
&lt;p&gt;- Equivalencia de expresiones algebraicas en la resolución de problemas basados en relaciones lineales y cuadráticas.&lt;/p&gt;
&lt;p&gt;- Estrategias de búsqueda de soluciones en ecuaciones y sistemas lineales y ecuaciones cuadráticas en situaciones de la vida cotidiana.&lt;/p&gt;
&lt;p&gt;- Ecuaciones: resolución mediante el uso de la tecnología.&lt;/p&gt;
&lt;ul&gt;
&lt;li&gt;Relaciones y funciones&lt;/li&gt;
&lt;/ul&gt;
&lt;p&gt;- Relaciones cuantitativas en situaciones de la vida cotidiana y clases de funciones que las modelizan.&lt;/p&gt;
&lt;p&gt;- Relaciones lineales y cuadráticas: identificación y comparación de diferentes modos de representación, tablas, gráficas o expresiones algebraicas, y sus propiedades a partir de ellas.&lt;/p&gt;
&lt;p&gt;- Estrategias de deducción de la información relevante de una función mediante el uso de diferentes representaciones simbólicas.&lt;/p&gt;
&lt;ul&gt;
&lt;li&gt;Pensamiento computacional&lt;br&gt;- Generalización y transferencia de procesos de resolución de problemas a otras situaciones.&lt;/li&gt;
&lt;/ul&gt;
&lt;p&gt;&lt;strong&gt;Bloque F. Sentido socioafectivo: &lt;/strong&gt;&lt;/p&gt;
&lt;ul&gt;
&lt;li&gt;Creencias, actitudes y emociones&lt;br&gt;- Gestión emocional: emociones que intervienen en el aprendizaje de las matemáticas. Autoconciencia y autorregulación.&lt;/li&gt;
&lt;li&gt;Trabajo en equipo y toma de decisiones&lt;br&gt;- Técnicas cooperativas para optimizar el trabajo en equipo y compartir y construir conocimiento matemático.- Conductas empáticas y estrategias de gestión de conflictos.&lt;/li&gt;
&lt;/ul&gt;
&lt;p&gt;&lt;/p&gt;&lt;p class="clearfix"&gt;&lt;/p&gt;&lt;/div&gt;
            &lt;/div&gt;&lt;/div&gt;&lt;/div&gt;</htmlView><jsonProperties>{"ideviceId":"20260424111208209RO5","textInfoDurationInput":"","textInfoDurationTextInput":"Duración","textInfoParticipantsInput":"","textInfoParticipantsTextInput":"Agrupamiento","textTextarea":"&lt;p&gt;&lt;/p&gt;\n&lt;table border=\"1\" style=\"width: 99.9778%; height: 2236.8px; border-color: #169179; border-style: outset;\"&gt;\n&lt;tbody&gt;\n&lt;tr style=\"height: 50.4px;\"&gt;\n&lt;td style=\"width: 39.0782%; height: 50.4px;\"&gt;&lt;strong&gt;COMPETENCIA ESPECÍFICA&lt;/strong&gt;&lt;/td&gt;\n&lt;td style=\"width: 14.4719%; height: 50.4px;\"&gt;&lt;strong&gt;DESCRIPTORES DEL PERFIL DE SALIDA&lt;/strong&gt;&lt;/td&gt;\n&lt;td style=\"width: 46.3163%; height: 50.4px;\"&gt;&lt;strong&gt;CRITERIOS DE EVALUACIÓN&lt;/strong&gt;&lt;/td&gt;\n&lt;/tr&gt;\n&lt;tr style=\"height: 362px;\"&gt;\n&lt;td style=\"width: 39.0782%; height: 362px;\"&gt;\n&lt;p&gt;&lt;strong&gt;CE1. Competencia específica &lt;/strong&gt;&lt;/p&gt;\n&lt;p&gt;Interpretar, modelizar y resolver problemas de la vida cotidiana propios de las matemáticas aplicando diferentes estrategias y formas de razonamiento para explorar distintas maneras de proceder y obtener posibles soluciones.  &lt;/p&gt;\n&lt;/td&gt;\n&lt;td style=\"width: 14.4719%; height: 362px;\"&gt;STEM1, STEM2, STEM3, STEM 4, CD2, CPSAA5, CE3, CCEC4.  &lt;/td&gt;\n&lt;td style=\"width: 46.3163%; height: 362px;\"&gt;CE1.1. Interpretar problemas matemáticos organizando los datos dados, estableciendo las relaciones entre ellos y comprendiendo las preguntas formuladas.  &lt;br /&gt;CE1.2. Aplicar herramientas y estrategias apropiadas que contribuyan a la resolución de problemas.   &lt;br /&gt;CE1.3. Obtener soluciones matemáticas de un problema activando los conocimientos y utilizando las herramientas tecnológicas necesarias.  &lt;/td&gt;\n&lt;/tr&gt;\n&lt;tr style=\"height: 274px;\"&gt;\n&lt;td style=\"width: 39.0782%; height: 274px;\"&gt;\n&lt;p&gt;&lt;strong&gt;CE2. Competencia específica&lt;/strong&gt; &lt;/p&gt;\n&lt;p&gt; Analizar las soluciones de un problema usando diferentes técnicas y herramientas, evaluando las respuestas obtenidas, para verificar su validez e idoneidad desde un punto de vista matemático y su repercusión global.  &lt;/p&gt;\n&lt;/td&gt;\n&lt;td style=\"width: 14.4719%; height: 274px;\"&gt;STEM1, STEM2, CD2, CPSAA4, CC3, CE3.  &lt;/td&gt;\n&lt;td style=\"width: 46.3163%; height: 274px;\"&gt;\n&lt;p&gt;CE2.2. Comprobar la validez de las soluciones de un problema y su coherencia en el contexto planteado, evaluando el alcance y repercusión de estas desde diferentes perspectivas (de género, de sostenibilidad, de consumo responsable, etc.).  &lt;/p&gt;\n&lt;/td&gt;\n&lt;/tr&gt;\n&lt;tr style=\"height: 578px;\"&gt;\n&lt;td style=\"width: 39.0782%; height: 578px;\"&gt;\n&lt;p&gt;&lt;strong&gt;CE 6.Competencia específica&lt;/strong&gt; &lt;/p&gt;\n&lt;p&gt;Identificar las matemáticas implicadas en otras materias y en situaciones reales, susceptibles de ser abordadas en términos matemáticos, interrelacionando conceptos y procedimientos para aplicarlos en situaciones diversas.  &lt;/p&gt;\n&lt;p&gt;&lt;br /&gt;&lt;/p&gt;\n&lt;/td&gt;\n&lt;td style=\"width: 14.4719%; height: 578px;\"&gt; STEM1, STEM3, CD3, CD5, CC4, CE2, CE3, CCEC1.  &lt;/td&gt;\n&lt;td style=\"width: 46.3163%; height: 578px;\"&gt;CE6.1. Reconocer situaciones susceptibles de ser formuladas y resueltas mediante herramientas y estrategias matemáticas, estableciendo conexiones entre el mundo real y las matemáticas y usando los procesos inherentes a la investigación: inferir, medir, comunicar, clasificar y predecir.  &lt;br /&gt;CE6.2. Identificar conexiones coherentes entre las matemáticas y otras materias resolviendo problemas contextualizados.  &lt;br /&gt;CE6.3. Reconocer la aportación de las matemáticas al progreso de la humanidad y su contribución a la superación de los retos que demanda la sociedad actual.  &lt;/td&gt;\n&lt;/tr&gt;\n&lt;tr style=\"height: 410px;\"&gt;\n&lt;td style=\"width: 39.0782%; height: 410px;\"&gt;\n&lt;p&gt;&lt;strong&gt;CE 7.Competencia específica&lt;/strong&gt; Representar, de forma individual y colectiva, conceptos, procedimientos, información y resultados matemáticos usando diferentes tecnologías, para visualizar ideas y estructurar procesos matemáticos.   &lt;/p&gt;\n&lt;p&gt;  &lt;/p&gt;\n&lt;/td&gt;\n&lt;td style=\"width: 14.4719%; height: 410px;\"&gt;STEM3, CD1, CD2, CD5, CE3, CCEC4.&lt;/td&gt;\n&lt;td style=\"width: 46.3163%; height: 410px;\"&gt;CE7.1. Representar conceptos, procedimientos, información y resultados matemáticos de modos distintos y con diferentes herramientas, incluidas las digitales, visualizando ideas, estructurando procesos matemáticos y valorando su utilidad para compartir información.  &lt;br /&gt;CE7.2. Elaborar representaciones matemáticas que ayuden en la búsqueda de estrategias de resolución de una situación problematizada.  &lt;/td&gt;\n&lt;/tr&gt;\n&lt;tr style=\"height: 458px;\"&gt;\n&lt;td style=\"width: 39.0782%; height: 458px;\"&gt;\n&lt;p&gt;&lt;strong&gt;CE 9. Competencia específica &lt;/strong&gt;&lt;/p&gt;\n&lt;p&gt; Desarrollar destrezas personales, identificando y gestionando emociones, poniendo en práctica estrategias de aceptación del error como parte del proceso de aprendizaje y adaptándose ante situaciones de incertidumbre, para mejorar la perseverancia en la consecución de objetivos y el disfrute en el aprendizaje de las matemáticas.  &lt;/p&gt;\n&lt;p&gt; &lt;/p&gt;\n&lt;/td&gt;\n&lt;td style=\"width: 14.4719%; height: 458px;\"&gt; STEM5, CPSAA1, CPSAA4, CPSAA5, CE2, CE3.&lt;/td&gt;\n&lt;td style=\"width: 46.3163%; height: 458px;\"&gt;CE9.1. Gestionar las emociones propias, desarrollar el autoconcepto matemático como herramienta generando expectativas positivas ante nuevos retos matemáticos.  &lt;br /&gt;CE9.2. Mostrar una actitud positiva y perseverante, aceptando la crítica razonada al hacer frente a las diferentes situaciones de aprendizaje de las matemáticas.  &lt;/td&gt;\n&lt;/tr&gt;\n&lt;tr style=\"height: 26px;\"&gt;\n&lt;td style=\"width: 39.0782%; height: 26px;\"&gt;\n&lt;p&gt;&lt;strong&gt;CE 10. Competencia específica&lt;/strong&gt; Desarrollar destrezas sociales reconociendo y respetando las emociones y experiencias ajenas, participando activa y reflexivamente en proyectos en equipos heterogéneos con roles asignados para construir una identidad positiva como estudiante de matemáticas, fomentar el bienestar personal y grupal y crear relaciones saludables.    &lt;/p&gt;\n&lt;/td&gt;\n&lt;td style=\"width: 14.4719%; height: 26px;\"&gt;CCL5, CP3, STEM3, CPSAA1, CPSAA3, CC2, CC3.&lt;/td&gt;\n&lt;td style=\"width: 46.3163%; height: 26px;\"&gt;CE10.1. Colaborar activamente y construir relaciones trabajando con las matemáticas en equipos heterogéneos, respetando diferentes opiniones, comunicándose de manera efectiva, pensando de forma crítica y creativa y tomando decisiones y realizando juicios informados.  &lt;br /&gt;CE10.2. Participar en el reparto de tareas que deban desarrollarse en equipo, aportando valor, favoreciendo la inclusión, la escucha activa, asumiendo el rol asignado y responsabilizándose de la propia contribución al equipo.  &lt;/td&gt;\n&lt;/tr&gt;\n&lt;tr style=\"height: 26px;\"&gt;\n&lt;td style=\"width: 39.0782%; height: 26px;\"&gt;&lt;br /&gt;&lt;/td&gt;\n&lt;td style=\"width: 14.4719%; height: 26px;\"&gt;&lt;br /&gt;&lt;/td&gt;\n&lt;td style=\"width: 46.3163%; height: 26px;\"&gt;&lt;br /&gt;&lt;/td&gt;\n&lt;/tr&gt;\n&lt;tr style=\"height: 26px;\"&gt;\n&lt;td style=\"width: 39.0782%; height: 26px;\"&gt;&lt;br /&gt;&lt;/td&gt;\n&lt;td style=\"width: 14.4719%; height: 26px;\"&gt;&lt;br /&gt;&lt;/td&gt;\n&lt;td style=\"width: 46.3163%; height: 26px;\"&gt;&lt;br /&gt;&lt;/td&gt;\n&lt;/tr&gt;\n&lt;tr style=\"height: 26.4px;\"&gt;\n&lt;td style=\"width: 39.0782%; height: 26.4px;\"&gt;&lt;br /&gt;&lt;/td&gt;\n&lt;td style=\"width: 14.4719%; height: 26.4px;\"&gt;&lt;br /&gt;&lt;/td&gt;\n&lt;td style=\"width: 46.3163%; height: 26.4px;\"&gt;&lt;/td&gt;\n&lt;/tr&gt;\n&lt;/tbody&gt;\n&lt;/table&gt;\n&lt;p&gt;&lt;br /&gt;&lt;br /&gt;&lt;strong&gt;SABERES BÁSICOS&lt;/strong&gt;&lt;/p&gt;\n&lt;p&gt;&lt;strong&gt;Bloque D. Sentido algebraico y pensamiento computacional:&lt;/strong&gt;&lt;/p&gt;\n&lt;ul&gt;\n&lt;li&gt;Patrones&lt;br /&gt;- Patrones: observación en casos sencillos.&lt;br /&gt;Bloque D. Sentido algebraico y pensamiento computacional: Modelo matemático&lt;br /&gt;- Modelización de situaciones de la vida cotidiana usando representaciones matemáticas y el lenguaje algebraico.- Estrategias de deducción de conclusiones razonables a partir de un modelo matemático.&lt;/li&gt;\n&lt;li&gt;Variable: Comprensión del concepto de variable en sus diferentes naturalezas.&lt;/li&gt;\n&lt;/ul&gt;\n&lt;ul&gt;\n&lt;li&gt; Igualdad y desigualdad:&lt;/li&gt;\n&lt;/ul&gt;\n&lt;p&gt;- Relaciones lineales y cuadráticas en situaciones de la vida cotidiana o matemáticamente relevantes: expresión mediante álgebra simbólica.&lt;/p&gt;\n&lt;p&gt;- Equivalencia de expresiones algebraicas en la resolución de problemas basados en relaciones lineales y cuadráticas.&lt;/p&gt;\n&lt;p&gt;- Estrategias de búsqueda de soluciones en ecuaciones y sistemas lineales y ecuaciones cuadráticas en situaciones de la vida cotidiana.&lt;/p&gt;\n&lt;p&gt;- Ecuaciones: resolución mediante el uso de la tecnología.&lt;/p&gt;\n&lt;ul&gt;\n&lt;li&gt;Relaciones y funciones&lt;/li&gt;\n&lt;/ul&gt;\n&lt;p&gt;- Relaciones cuantitativas en situaciones de la vida cotidiana y clases de funciones que las modelizan.&lt;/p&gt;\n&lt;p&gt;- Relaciones lineales y cuadráticas: identificación y comparación de diferentes modos de representación, tablas, gráficas o expresiones algebraicas, y sus propiedades a partir de ellas.&lt;/p&gt;\n&lt;p&gt;- Estrategias de deducción de la información relevante de una función mediante el uso de diferentes representaciones simbólicas.&lt;/p&gt;\n&lt;ul&gt;\n&lt;li&gt;Pensamiento computacional&lt;br /&gt;- Generalización y transferencia de procesos de resolución de problemas a otras situaciones.&lt;/li&gt;\n&lt;/ul&gt;\n&lt;p&gt;&lt;strong&gt;Bloque F. Sentido socioafectivo: &lt;/strong&gt;&lt;/p&gt;\n&lt;ul&gt;\n&lt;li&gt;Creencias, actitudes y emociones&lt;br /&gt;- Gestión emocional: emociones que intervienen en el aprendizaje de las matemáticas. Autoconciencia y autorregulación.&lt;/li&gt;\n&lt;li&gt;Trabajo en equipo y toma de decisiones&lt;br /&gt;- Técnicas cooperativas para optimizar el trabajo en equipo y compartir y construir conocimiento matemático.- Conductas empáticas y estrategias de gestión de conflictos.&lt;/li&gt;\n&lt;/ul&gt;\n&lt;p&gt;&lt;/p&gt;","textFeedbackInput":"Mostrar retroalimentación","textFeedbackTextarea":""}</jsonProperties><odeComponentsOrder>1</odeComponentsOrder><odeComponentsProperties><odeComponentsProperty><key>visibility</key><value>true</value></odeComponentsProperty><odeComponentsProperty><key>teacherOnly</key><value>false</value></odeComponentsProperty><odeComponentsProperty><key>identifier</key><value/></odeComponentsProperty><odeComponentsProperty><key>cssClass</key><value/></odeComponentsProperty></odeComponentsProperties></odeComponent></odeComponents></odePagStructure></odePagStructures></odeNavStructure><odeNavStructure><odePageId>20260430094221RKIKLS</odePageId><odeParentPageId>20260430094221FTPHYO</odeParentPageId><pageName>3. Metodologías activas</pageName><odeNavStructureOrder>3</odeNavStructureOrder><odeNavStructureProperties><odeNavStructureProperty><key>titleNode</key><value/></odeNavStructureProperty><odeNavStructureProperty><key>hidePageTitle</key><value>false</value></odeNavStructureProperty><odeNavStructureProperty><key>titleHtml</key><value/></odeNavStructureProperty><odeNavStructureProperty><key>editableInPage</key><value>false</value></odeNavStructureProperty><odeNavStructureProperty><key>titlePage</key><value>3. Metodologías activas</value></odeNavStructureProperty><odeNavStructureProperty><key>visibility</key><value>true</value></odeNavStructureProperty><odeNavStructureProperty><key>highlight</key><value>false</value></odeNavStructureProperty><odeNavStructureProperty><key>description</key><value/></odeNavStructureProperty></odeNavStructureProperties><odePagStructures><odePagStructure><odePageId>20260430094221RKIKLS</odePageId><odeBlockId>20260430094221DIWYSM</odeBlockId><blockName>Texto</blockName><iconName/><odePagStructureOrder>1</odePagStructureOrder><odePagStructureProperties><odePagStructureProperty><key>visibility</key><value>true</value></odePagStructureProperty><odePagStructureProperty><key>teacherOnly</key><value>false</value></odePagStructureProperty><odePagStructureProperty><key>allowToggle</key><value>true</value></odePagStructureProperty><odePagStructureProperty><key>minimized</key><value>false</value></odePagStructureProperty><odePagStructureProperty><key>identifier</key><value/></odePagStructureProperty><odePagStructureProperty><key>cssClass</key><value/></odePagStructureProperty></odePagStructureProperties><odeComponents><odeComponent><odePageId>20260430094221RKIKLS</odePageId><odeBlockId>20260430094221DIWYSM</odeBlockId><odeIdeviceId>20260424111142273E3K</odeIdeviceId><odeIdeviceTypeName>text</odeIdeviceTypeName><htmlView>&lt;div class="exe-text-template"&gt;&lt;div class="textIdeviceContent"&gt;
            &lt;div class="exe-text-activity"&gt;
                &lt;div&gt;&lt;p&gt;En esta SdA se utilizarán las siguientes metodologías activas:&amp;nbsp;&lt;/p&gt;
&lt;ul&gt;
&lt;li&gt;Aprendizaje basado en proyectos.&lt;/li&gt;
&lt;li&gt;Aprendizaje basado en problemas.&lt;/li&gt;
&lt;li&gt;Aprendizaje cooperativo/ colaborativo.&lt;/li&gt;
&lt;li&gt;Gamificación.&lt;/li&gt;
&lt;/ul&gt;&lt;p class="clearfix"&gt;&lt;/p&gt;&lt;/div&gt;
            &lt;/div&gt;&lt;/div&gt;&lt;/div&gt;</htmlView><jsonProperties>{"ideviceId":"20260424111142273E3K","textInfoDurationInput":"","textInfoDurationTextInput":"Duración","textInfoParticipantsInput":"","textInfoParticipantsTextInput":"Agrupamiento","textTextarea":"&lt;p&gt;En esta SdA se utilizarán las siguientes metodologías activas: &lt;/p&gt;\n&lt;ul&gt;\n&lt;li&gt;Aprendizaje basado en proyectos.&lt;/li&gt;\n&lt;li&gt;Aprendizaje basado en problemas.&lt;/li&gt;\n&lt;li&gt;Aprendizaje cooperativo/ colaborativo.&lt;/li&gt;\n&lt;li&gt;Gamificación.&lt;/li&gt;\n&lt;/ul&gt;","textFeedbackInput":"Mostrar retroalimentación","textFeedbackTextarea":""}</jsonProperties><odeComponentsOrder>1</odeComponentsOrder><odeComponentsProperties><odeComponentsProperty><key>visibility</key><value>true</value></odeComponentsProperty><odeComponentsProperty><key>teacherOnly</key><value>false</value></odeComponentsProperty><odeComponentsProperty><key>identifier</key><value/></odeComponentsProperty><odeComponentsProperty><key>cssClass</key><value/></odeComponentsProperty></odeComponentsProperties></odeComponent></odeComponents></odePagStructure></odePagStructures></odeNavStructure><odeNavStructure><odePageId>20260430094221YFRLDB</odePageId><odeParentPageId>20260430094221FTPHYO</odeParentPageId><pageName>4. Vinculación con los proyectos y programas del centro</pageName><odeNavStructureOrder>4</odeNavStructureOrder><odeNavStructureProperties><odeNavStructureProperty><key>titleNode</key><value/></odeNavStructureProperty><odeNavStructureProperty><key>hidePageTitle</key><value>false</value></odeNavStructureProperty><odeNavStructureProperty><key>titleHtml</key><value/></odeNavStructureProperty><odeNavStructureProperty><key>editableInPage</key><value>false</value></odeNavStructureProperty><odeNavStructureProperty><key>titlePage</key><value>4. Vinculación con los proyectos y programas del centro</value></odeNavStructureProperty><odeNavStructureProperty><key>visibility</key><value>true</value></odeNavStructureProperty><odeNavStructureProperty><key>highlight</key><value>false</value></odeNavStructureProperty><odeNavStructureProperty><key>description</key><value/></odeNavStructureProperty></odeNavStructureProperties><odePagStructures><odePagStructure><odePageId>20260430094221YFRLDB</odePageId><odeBlockId>20260430094221TZBQQF</odeBlockId><blockName>Texto</blockName><iconName/><odePagStructureOrder>1</odePagStructureOrder><odePagStructureProperties><odePagStructureProperty><key>visibility</key><value>true</value></odePagStructureProperty><odePagStructureProperty><key>teacherOnly</key><value>false</value></odePagStructureProperty><odePagStructureProperty><key>allowToggle</key><value>true</value></odePagStructureProperty><odePagStructureProperty><key>minimized</key><value>false</value></odePagStructureProperty><odePagStructureProperty><key>identifier</key><value/></odePagStructureProperty><odePagStructureProperty><key>cssClass</key><value/></odePagStructureProperty></odePagStructureProperties><odeComponents><odeComponent><odePageId>20260430094221YFRLDB</odePageId><odeBlockId>20260430094221TZBQQF</odeBlockId><odeIdeviceId>20260428112741625TO0</odeIdeviceId><odeIdeviceTypeName>text</odeIdeviceTypeName><htmlView>&lt;div class="exe-text-template"&gt;&lt;div class="textIdeviceContent"&gt;
            &lt;div class="exe-text-activity"&gt;
                &lt;div&gt;&lt;p&gt;Esta situación de aprendizaje está vinculada al Proyecto de Educación para la Salud del centro, participando también en el Programa Escolar de consumo de frutas, leche y productos lácteos del Principado de Asturias.&lt;/p&gt;&lt;p class="clearfix"&gt;&lt;/p&gt;&lt;/div&gt;
            &lt;/div&gt;&lt;/div&gt;&lt;/div&gt;</htmlView><jsonProperties>{"ideviceId":"20260428112741625TO0","textInfoDurationInput":"","textInfoDurationTextInput":"Duración","textInfoParticipantsInput":"","textInfoParticipantsTextInput":"Agrupamiento","textTextarea":"&lt;p&gt;Esta situación de aprendizaje está vinculada al Proyecto de Educación para la Salud del centro, participando también en el Programa Escolar de consumo de frutas, leche y productos lácteos del Principado de Asturias.&lt;/p&gt;","textFeedbackInput":"Mostrar retroalimentación","textFeedbackTextarea":""}</jsonProperties><odeComponentsOrder>1</odeComponentsOrder><odeComponentsProperties><odeComponentsProperty><key>visibility</key><value>true</value></odeComponentsProperty><odeComponentsProperty><key>teacherOnly</key><value>false</value></odeComponentsProperty><odeComponentsProperty><key>identifier</key><value/></odeComponentsProperty><odeComponentsProperty><key>cssClass</key><value/></odeComponentsProperty></odeComponentsProperties></odeComponent></odeComponents></odePagStructure></odePagStructures></odeNavStructure><odeNavStructure><odePageId>20260430094221DKNJFD</odePageId><odeParentPageId>20260430094221FTPHYO</odeParentPageId><pageName>5. Actividades complementarias y extraescolares</pageName><odeNavStructureOrder>5</odeNavStructureOrder><odeNavStructureProperties><odeNavStructureProperty><key>titleNode</key><value/></odeNavStructureProperty><odeNavStructureProperty><key>hidePageTitle</key><value>false</value></odeNavStructureProperty><odeNavStructureProperty><key>titleHtml</key><value/></odeNavStructureProperty><odeNavStructureProperty><key>editableInPage</key><value>false</value></odeNavStructureProperty><odeNavStructureProperty><key>titlePage</key><value>5. Actividades complementarias y extraescolares</value></odeNavStructureProperty><odeNavStructureProperty><key>visibility</key><value>true</value></odeNavStructureProperty><odeNavStructureProperty><key>highlight</key><value>false</value></odeNavStructureProperty><odeNavStructureProperty><key>description</key><value/></odeNavStructureProperty></odeNavStructureProperties><odePagStructures><odePagStructure><odePageId>20260430094221DKNJFD</odePageId><odeBlockId>20260430094221AGAMAH</odeBlockId><blockName>Texto</blockName><iconName/><odePagStructureOrder>1</odePagStructureOrder><odePagStructureProperties><odePagStructureProperty><key>visibility</key><value>true</value></odePagStructureProperty><odePagStructureProperty><key>teacherOnly</key><value>false</value></odePagStructureProperty><odePagStructureProperty><key>allowToggle</key><value>true</value></odePagStructureProperty><odePagStructureProperty><key>minimized</key><value>false</value></odePagStructureProperty><odePagStructureProperty><key>identifier</key><value/></odePagStructureProperty><odePagStructureProperty><key>cssClass</key><value/></odePagStructureProperty></odePagStructureProperties><odeComponents><odeComponent><odePageId>20260430094221DKNJFD</odePageId><odeBlockId>20260430094221AGAMAH</odeBlockId><odeIdeviceId>202604281130441769XB</odeIdeviceId><odeIdeviceTypeName>text</odeIdeviceTypeName><htmlView>&lt;div class="exe-text-template"&gt;&lt;div class="textIdeviceContent"&gt;
            &lt;div class="exe-text-activity"&gt;
                &lt;div&gt;&lt;p&gt;En esta SdA, se propone como actividad complementaria:&lt;/p&gt;
&lt;p&gt;-Visita a la quesería de "Los Caserinos" y a la plantación de arándanos "El Bregón".&lt;/p&gt;
&lt;p&gt;&lt;/p&gt;
&lt;p&gt;No hay actividades extraescolares relacionadas.&lt;/p&gt;&lt;p class="clearfix"&gt;&lt;/p&gt;&lt;/div&gt;
            &lt;/div&gt;&lt;/div&gt;&lt;/div&gt;</htmlView><jsonProperties>{"ideviceId":"202604281130441769XB","textInfoDurationInput":"","textInfoDurationTextInput":"Duración","textInfoParticipantsInput":"","textInfoParticipantsTextInput":"Agrupamiento","textTextarea":"&lt;p&gt;En esta SdA, se propone como actividad complementaria:&lt;/p&gt;\n&lt;p&gt;-Visita a la quesería de \"Los Caserinos\" y a la plantación de arándanos \"El Bregón\".&lt;/p&gt;\n&lt;p&gt;&lt;/p&gt;\n&lt;p&gt;No hay actividades extraescolares relacionadas.&lt;/p&gt;","textFeedbackInput":"Mostrar retroalimentación","textFeedbackTextarea":""}</jsonProperties><odeComponentsOrder>1</odeComponentsOrder><odeComponentsProperties><odeComponentsProperty><key>visibility</key><value>true</value></odeComponentsProperty><odeComponentsProperty><key>teacherOnly</key><value>false</value></odeComponentsProperty><odeComponentsProperty><key>identifier</key><value/></odeComponentsProperty><odeComponentsProperty><key>cssClass</key><value/></odeComponentsProperty></odeComponentsProperties></odeComponent></odeComponents></odePagStructure></odePagStructures></odeNavStructure><odeNavStructure><odePageId>20260430094221HYSLIS</odePageId><odeParentPageId>20260430094221FTPHYO</odeParentPageId><pageName>6. Atribución y descarga</pageName><odeNavStructureOrder>6</odeNavStructureOrder><odeNavStructureProperties><odeNavStructureProperty><key>titleNode</key><value/></odeNavStructureProperty><odeNavStructureProperty><key>hidePageTitle</key><value>false</value></odeNavStructureProperty><odeNavStructureProperty><key>titleHtml</key><value/></odeNavStructureProperty><odeNavStructureProperty><key>editableInPage</key><value>false</value></odeNavStructureProperty><odeNavStructureProperty><key>titlePage</key><value>6. Atribución y descarga</value></odeNavStructureProperty><odeNavStructureProperty><key>visibility</key><value>true</value></odeNavStructureProperty><odeNavStructureProperty><key>highlight</key><value>false</value></odeNavStructureProperty><odeNavStructureProperty><key>description</key><value/></odeNavStructureProperty></odeNavStructureProperties><odePagStructures><odePagStructure><odePageId>20260430094221HYSLIS</odePageId><odeBlockId>20260430094221SJRQYZ</odeBlockId><blockName>Texto</blockName><iconName/><odePagStructureOrder>1</odePagStructureOrder><odePagStructureProperties><odePagStructureProperty><key>visibility</key><value>true</value></odePagStructureProperty><odePagStructureProperty><key>teacherOnly</key><value>false</value></odePagStructureProperty><odePagStructureProperty><key>allowToggle</key><value>true</value></odePagStructureProperty><odePagStructureProperty><key>minimized</key><value>false</value></odePagStructureProperty><odePagStructureProperty><key>identifier</key><value/></odePagStructureProperty><odePagStructureProperty><key>cssClass</key><value/></odePagStructureProperty></odePagStructureProperties><odeComponents><odeComponent><odePageId>20260430094221HYSLIS</odePageId><odeBlockId>20260430094221SJRQYZ</odeBlockId><odeIdeviceId>20260424111444161DRO</odeIdeviceId><odeIdeviceTypeName>text</odeIdeviceTypeName><htmlView>&lt;div class="exe-text-template"&gt;&lt;div class="textIdeviceContent"&gt;
            &lt;div class="exe-text-activity"&gt;
                &lt;div&gt;&lt;p class="clearfix"&gt;&lt;/p&gt;&lt;/div&gt;
            &lt;/div&gt;&lt;/div&gt;&lt;/div&gt;</htmlView><jsonProperties>{"ideviceId":"20260424111444161DRO","textInfoDurationInput":"","textInfoDurationTextInput":"Duración","textInfoParticipantsInput":"","textInfoParticipantsTextInput":"Agrupamiento","textTextarea":"","textFeedbackInput":"Mostrar retroalimentación","textFeedbackTextarea":""}</jsonProperties><odeComponentsOrder>1</odeComponentsOrder><odeComponentsProperties><odeComponentsProperty><key>visibility</key><value>true</value></odeComponentsProperty><odeComponentsProperty><key>teacherOnly</key><value>false</value></odeComponentsProperty><odeComponentsProperty><key>identifier</key><value/></odeComponentsProperty><odeComponentsProperty><key>cssClass</key><value/></odeComponentsProperty></odeComponentsProperties></odeComponent></odeComponents></odePagStructure><odePagStructure><odePageId>20260430094221HYSLIS</odePageId><odeBlockId>20260430094221UWHYIW</odeBlockId><blockName>Descargar el archivo fuente</blockName><iconName/><odePagStructureOrder>2</odePagStructureOrder><odePagStructureProperties><odePagStructureProperty><key>visibility</key><value>true</value></odePagStructureProperty><odePagStructureProperty><key>teacherOnly</key><value>false</value></odePagStructureProperty><odePagStructureProperty><key>allowToggle</key><value>true</value></odePagStructureProperty><odePagStructureProperty><key>minimized</key><value>false</value></odePagStructureProperty><odePagStructureProperty><key>identifier</key><value/></odePagStructureProperty><odePagStructureProperty><key>cssClass</key><value/></odePagStructureProperty></odePagStructureProperties><odeComponents><odeComponent><odePageId>20260430094221HYSLIS</odePageId><odeBlockId>20260430094221UWHYIW</odeBlockId><odeIdeviceId>20260430105354525NO9</odeIdeviceId><odeIdeviceTypeName>download-source-file</odeIdeviceTypeName><htmlView>&lt;div class="exe-download-package-instructions"&gt;&lt;table class="exe-table exe-package-info"&gt;&lt;caption&gt;Información general sobre este recurso educativo&lt;/caption&gt;
&lt;tbody&gt;
&lt;tr&gt;
&lt;th&gt;Título&lt;/th&gt;
&lt;td&gt;SdA Funciones&lt;/td&gt;
&lt;/tr&gt;
&lt;tr&gt;
&lt;th&gt;Descripción&lt;/th&gt;
&lt;td&gt;Matemáticas 2ºESO&lt;/td&gt;
&lt;/tr&gt;
&lt;tr&gt;
&lt;th&gt;Autoría&lt;/th&gt;
&lt;td&gt;Alazne Ceñal Ordóñez&lt;/td&gt;
&lt;/tr&gt;
&lt;tr&gt;
&lt;th&gt;Licencia&lt;/th&gt;
&lt;td&gt;creative commons: attribution - share alike 4.0&lt;/td&gt;
&lt;/tr&gt;
&lt;/tbody&gt;
&lt;/table&gt;
&lt;p style="text-align: center;"&gt;Este contenido fue creado con &lt;a href="http://exelearning.net/"&gt;eXeLearning&lt;/a&gt;, el editor libre y de fuente abierta diseñado para crear recursos educativos.&lt;/p&gt;&lt;/div&gt;&lt;p class="exe-download-package-link"&gt;&lt;a download="exe-package:elp-name" href="exe-package:elp" style="background-color:#107275;color:#ffffff;"&gt;Descargar el archivo .elpx&lt;/a&gt;&lt;/p&gt;</htmlView><jsonProperties/><odeComponentsOrder>1</odeComponentsOrder><odeComponentsProperties><odeComponentsProperty><key>visibility</key><value>true</value></odeComponentsProperty><odeComponentsProperty><key>teacherOnly</key><value>false</value></odeComponentsProperty><odeComponentsProperty><key>identifier</key><value/></odeComponentsProperty><odeComponentsProperty><key>cssClass</key><value/></odeComponentsProperty></odeComponentsProperties></odeComponent></odeComponents></odePagStructure></odePagStructures></odeNavStructure></odeNavStructures></ode>
